{"cameraMode":{"drawMode":0,"name":"Shaded","section":"Shading Mode"},"sceneLighting":false,"audioPlay":false,"sceneViewState":{"showFog":true,"showMaterialUpdate":false,"showSkybox":false,"showFlares":true,"showImageEffects":true,"showParticleSystems":true,"showVisualEffectGraphs":true,"m_FxEnabled":true},"in2DMode":false,"pivot":{"x":7.717517852783203,"y":-10.442523002624512,"z":-36.190147399902347},"rotation":{"x":0.0321204774081707,"y":-0.26311758160591128,"z":0.008761581033468247,"w":0.9642024636268616},"size":6.888611793518066,"orthographic":true}